gameanalysis/__init__.py
gameanalysis/__main__.py
gameanalysis/aggfn.py
gameanalysis/bootstrap.py
gameanalysis/canongame.py
gameanalysis/collect.py
gameanalysis/dominance.py
gameanalysis/fixedpoint.py
gameanalysis/gambit.py
gameanalysis/gamegen.py
gameanalysis/gamereader.py
gameanalysis/learning.py
gameanalysis/matgame.py
gameanalysis/nash.py
gameanalysis/paygame.py
gameanalysis/regret.py
gameanalysis/restrict.py
gameanalysis/rsgame.py
gameanalysis/scriptutils.py
gameanalysis/trace.py
gameanalysis/utils.py
gameanalysis/reduction/__init__.py
gameanalysis/reduction/_common.py
gameanalysis/reduction/deviation_preserving.py
gameanalysis/reduction/hierarchical.py
gameanalysis/reduction/identity.py
gameanalysis/reduction/twins.py
gameanalysis/script/__init__.py
gameanalysis/script/analyze.py
gameanalysis/script/boot.py
gameanalysis/script/conv.py
gameanalysis/script/dom.py
gameanalysis/script/gen.py
gameanalysis/script/learning.py
gameanalysis/script/nash.py
gameanalysis/script/pay.py
gameanalysis/script/red.py
gameanalysis/script/reg.py
gameanalysis/script/rest.py
gameanalysis/script/sample.py
gameanalysis-8.1.0.dist-info/LICENSE
gameanalysis-8.1.0.dist-info/METADATA
gameanalysis-8.1.0.dist-info/WHEEL
gameanalysis-8.1.0.dist-info/entry_points.txt
gameanalysis-8.1.0.dist-info/top_level.txt
gameanalysis-8.1.0.dist-info/RECORD
