Metadata-Version: 2.1
Name: gameanalysis
Version: 8.1.0
Summary: A python module for analyzing sparse and empirical games
Home-page: https://github.com/egtaonline/gameanalysis.git
Author: Strategic Reasoning Group
Author-email: strategic.reasoning.group@umich.edu
License: Apache 2.0
Platform: UNKNOWN
Requires-Dist: numpy (~=1.18.0)
Requires-Dist: scipy (~=1.5)
Requires-Dist: scikit-learn (~=0.23)
Provides-Extra: dev
Requires-Dist: autograd (~=1.3) ; extra == 'dev'
Requires-Dist: black (~=20.8b) ; extra == 'dev'
Requires-Dist: ipython (~=7.18) ; extra == 'dev'
Requires-Dist: mock (~=4.0) ; extra == 'dev'
Requires-Dist: pylint (~=2.6) ; extra == 'dev'
Requires-Dist: pytest-cov (~=2.10) ; extra == 'dev'
Requires-Dist: pytest-xdist (~=2.1) ; extra == 'dev'
Requires-Dist: pytest (~=6.1) ; extra == 'dev'
Requires-Dist: sphinx (~=3.2) ; extra == 'dev'
Requires-Dist: tabulate (~=0.8) ; extra == 'dev'
Requires-Dist: twine (~=3.2) ; extra == 'dev'
Requires-Dist: wheel (~=0.35) ; extra == 'dev'
Provides-Extra: nn
Requires-Dist: Keras (~=2.4) ; extra == 'nn'
Requires-Dist: tensorflow (~=2.3) ; extra == 'nn'
